explorationViewer/__init__.py
explorationViewer/__main__.py
explorationViewer/viewer/LICENSE-d3.txt
explorationViewer/viewer/LICENSE-pyodide.txt
explorationViewer/viewer/d3.v7.min.js
explorationViewer/viewer/diwl_Peter.dcg
explorationViewer/viewer/example.exp
explorationViewer/viewer/favicon.ico
explorationViewer/viewer/favicon.ico~
explorationViewer/viewer/help.html
explorationViewer/viewer/htr_Peter.dcg
explorationViewer/viewer/index.html
explorationViewer/viewer/pyodide-core-0.23.4.tar.bz2
explorationViewer/viewer/redirect.html
explorationViewer/viewer/viewer.py
explorationViewer/viewer/__pycache__/viewer.cpython-310.pyc
explorationViewer/viewer/pyodide/PIL-9.1.1-cp311-cp311-emscripten_3_1_32_wasm32.whl
explorationViewer/viewer/pyodide/cycler-0.11.0-py3-none-any.whl
explorationViewer/viewer/pyodide/decorator-5.1.1-py3-none-any.whl
explorationViewer/viewer/pyodide/distutils-1.0.0.zip
explorationViewer/viewer/pyodide/exploration-0.7.5-py3-none-any.whl
explorationViewer/viewer/pyodide/fonttools-4.39.3-py3-none-any.whl
explorationViewer/viewer/pyodide/kiwisolver-1.4.4-cp311-cp311-emscripten_3_1_32_wasm32.whl
explorationViewer/viewer/pyodide/matplotlib-3.5.2-cp311-cp311-emscripten_3_1_32_wasm32.whl
explorationViewer/viewer/pyodide/matplotlib_pyodide-0.1.1-py3-none-any.whl
explorationViewer/viewer/pyodide/micropip-0.3.0-py3-none-any.whl
explorationViewer/viewer/pyodide/networkx-3.4.2-py3-none-any.whl
explorationViewer/viewer/pyodide/numpy-1.24.2-cp311-cp311-emscripten_3_1_32_wasm32.whl
explorationViewer/viewer/pyodide/package.json
explorationViewer/viewer/pyodide/packaging-23.0-py3-none-any.whl
explorationViewer/viewer/pyodide/pyodide.asm.js
explorationViewer/viewer/pyodide/pyodide.asm.wasm
explorationViewer/viewer/pyodide/pyodide.js
explorationViewer/viewer/pyodide/pyodide.mjs
explorationViewer/viewer/pyodide/pyparsing-3.0.9-py3-none-any.whl
explorationViewer/viewer/pyodide/python_dateutil-2.8.2-py2.py3-none-any.whl
explorationViewer/viewer/pyodide/python_stdlib.zip
explorationViewer-0.3.dist-info/LICENSE.txt
explorationViewer-0.3.dist-info/METADATA
explorationViewer-0.3.dist-info/WHEEL
explorationViewer-0.3.dist-info/top_level.txt
explorationViewer-0.3.dist-info/RECORD
