Metadata-Version: 2.1
Name: explorationViewer
Version: 0.3
Summary: Tool for interactively visualizing decision graphs produced by the 'exploration' module. By default runs a local HTTP server to serve an HTML file and opens that file in the browser.
Home-page: https://cs.wellesley.edu/~pmwh/mvmap/egviewer/docs/explorationViewer
Author: Peter Mawhorter
Author-email: pmawhort@wellesley.edu
License: BSD 3-Clause License
Classifier: Programming Language :: Python :: 3 :: Only
Classifier: Development Status :: 3 - Alpha
Classifier: Intended Audience :: Developers
Classifier: Intended Audience :: Science/Research
Classifier: License :: OSI Approved :: BSD License
Classifier: Operating System :: OS Independent
Classifier: Natural Language :: English
Classifier: Topic :: Games/Entertainment
Classifier: Topic :: Scientific/Engineering :: Artificial Intelligence
Classifier: Topic :: Scientific/Engineering :: Visualization
Requires-Python: >=3.10
License-File: LICENSE.txt
Requires-Dist: exploration>=0.7.5
Provides-Extra: test
Requires-Dist: pytest; extra == "test"
